selenium_simulate_ui/__init__.py
selenium_simulate_ui/template.py
selenium_simulate_ui-0.1.5.dist-info/METADATA
selenium_simulate_ui-0.1.5.dist-info/WHEEL
selenium_simulate_ui-0.1.5.dist-info/top_level.txt
selenium_simulate_ui-0.1.5.dist-info/RECORD
